{"txn":{"appId":"a4826196-7184-4c40-b01b-07c207e5bc41","version":1,"lastUpdated":1750528938027}}
{"add":{"path":"part-00000-7e4cf132-427c-40c8-bb07-53b00085fade-c000.snappy.parquet","partitionValues":{},"size":20621,"modificationTime":1750528937831,"dataChange":true,"stats":"{\"numRecords\":1729,\"minValues\":{\"timestamp\":\"2001-01-09T23:16:59.000+05:30\",\"Primary_Type\":\"ARSON\",\"Location_Description\":\"ABANDONED BUILDING\",\"Arrest\":\"FALSE\",\"Domestic\":\"FALSE\",\"District\":\"1\",\"Year\":\"2001\"},\"maxValues\":{\"timestamp\":\"2007-12-25T23:00:00.000+05:30\",\"Primary_Type\":\"WEAPONS VIOLATION\",\"Location_Description\":\"WAREHOUSE\",\"Arrest\":\"True\",\"Domestic\":\"True\",\"District\":\"9.0\",\"Year\":\"2007.0\"},\"nullCount\":{\"timestamp\":532,\"Primary_Type\":0,\"Location_Description\":0,\"Arrest\":0,\"Domestic\":0,\"District\":0,\"Year\":0}}"}}
{"commitInfo":{"timestamp":1750528938027,"operation":"STREAMING UPDATE","operationParameters":{"outputMode":"Append","queryId":"a4826196-7184-4c40-b01b-07c207e5bc41","epochId":"1"},"readVersion":0,"isolationLevel":"Serializable","isBlindAppend":true,"operationMetrics":{"numRemovedFiles":"0","numOutputRows":"1729","numOutputBytes":"20621","numAddedFiles":"1"},"engineInfo":"Apache-Spark/3.3.2 Delta-Lake/1.2.1","txnId":"5b1baf8e-5e79-4c2b-b9b9-33f6d8fc2606"}}
